GoRDB/GoRDB.py
GoRDB/__init__.py
GoRDB-6.3.dist-info/LICENSE
GoRDB-6.3.dist-info/METADATA
GoRDB-6.3.dist-info/WHEEL
GoRDB-6.3.dist-info/top_level.txt
GoRDB-6.3.dist-info/RECORD
