Metadata-Version: 2.1
Name: GoRDB
Version: 6.3
Summary: A lightweight python library for implementing GraphQL on Relational DB Tables in few steps using python dicts. The library is built over strawberry-graphql for creating graphQL schema from dataclasses
Home-page: https://github.com/RajaGanapathyM/GoRDB
Author: RajaGanapathyM
Author-email: rganapathy6@gmail.com
License: UNKNOWN
Download-URL: https://github.com/RajaGanapathyM/GoRDB/archive/refs/tags/v.0.1.tar.gz
Keywords: GraphQL,RDB
Platform: UNKNOWN
Classifier: License :: OSI Approved :: GNU General Public License v3 (GPLv3)
License-File: LICENSE
